bio_test_artifacts/__init__.py
bio_test_artifacts/_loader.py
bio_test_artifacts/generate/__init__.py
bio_test_artifacts/generate/counts.py
bio_test_artifacts/generate/fasta.py
bio_test_artifacts/generate/fastq.py
bio_test_artifacts/prebuilt/__init__.py
bio_test_artifacts/prebuilt/_yeast_fasta.py
bio_test_artifacts/prebuilt/bam_sam.py
bio_test_artifacts/prebuilt/counts.py
bio_test_artifacts/prebuilt/fasta.py
bio_test_artifacts/prebuilt/fastq.py
bio_test_artifacts/prebuilt/gtf_gff.py
bio_test_artifacts/prebuilt/artifacts/GSE125162_counts_chr01.h5ad.gz
bio_test_artifacts/prebuilt/artifacts/GSE125162_counts_chr01.hdf5.gz
bio_test_artifacts/prebuilt/artifacts/GSE125162_counts_chr01.mtx.gz
bio_test_artifacts/prebuilt/artifacts/GSE125162_counts_chr01.tsv
bio_test_artifacts/prebuilt/artifacts/GSE125162_counts_chr01.tsv.gz
bio_test_artifacts/prebuilt/artifacts/GSE125162_counts_chr01_features.tsv.gz
bio_test_artifacts/prebuilt/artifacts/GSE125162_counts_chr01_genes.tsv.gz
bio_test_artifacts/prebuilt/artifacts/GSE135430_counts_TPM.tsv
bio_test_artifacts/prebuilt/artifacts/GSE135430_counts_chr01_TPM.tsv
bio_test_artifacts/prebuilt/artifacts/SRR1569870_1.fastq.gz
bio_test_artifacts/prebuilt/artifacts/SRR1569870_2.fastq.gz
bio_test_artifacts/prebuilt/artifacts/SRR1569870_chr01.bam
bio_test_artifacts/prebuilt/artifacts/SRR1569870_chr01.sam
bio_test_artifacts/prebuilt/artifacts/SRR1569870_chr01.sorted.bam
bio_test_artifacts/prebuilt/artifacts/yeast_chr01.fasta
bio_test_artifacts/prebuilt/artifacts/yeast_chr01.gff
bio_test_artifacts/prebuilt/artifacts/yeast_chr01.gtf
bio_test_artifacts/prebuilt/artifacts/yeast_chr01_protein.fasta
bio_test_artifacts-0.1.0.dist-info/LICENSE
bio_test_artifacts-0.1.0.dist-info/METADATA
bio_test_artifacts-0.1.0.dist-info/WHEEL
bio_test_artifacts-0.1.0.dist-info/top_level.txt
bio_test_artifacts-0.1.0.dist-info/RECORD
