Metadata-Version: 2.1
Name: bio-test-artifacts
Version: 0.1.0
Summary: Test Artifacts for Biology
Home-page: https://github.com/asistradition/bio-test-artifacts
Author: Chris Jackson
Author-email: cj59@nyu.edu
Maintainer: Chris Jackson
Maintainer-email: cj59@nyu.edu
License: UNKNOWN
Platform: UNKNOWN
Classifier: Programming Language :: Python :: 3
Classifier: License :: OSI Approved :: MIT License
Classifier: Operating System :: OS Independent
Classifier: Development Status :: 3 - Alpha
Requires-Python: >=3.5
Requires-Dist: numpy
Requires-Dist: pandas
